async_signals/__init__.py
async_signals/dispatcher.py
async_signals/license.txt
async_signals/py.typed
async_signals/utils.py
async_signals-0.3.1.dist-info/licenses/LICENSE
async_signals-0.3.1.dist-info/WHEEL
async_signals-0.3.1.dist-info/METADATA
async_signals-0.3.1.dist-info/RECORD
