Metadata-Version: 2.4
Name: async-signals
Version: 0.3.1
Summary: Async version of the Django signals class - for usage in for example FastAPI.
Author: TEAM23 GmbH
Author-email: TEAM23 GmbH <info@team23.de>
License-Expression: BSD-3-Clause
License-File: LICENSE
Requires-Python: >=3.10
Project-URL: Repository, https://github.com/team23/async-signals
